<?xml version="1.0" encoding="utf-8"?>
<!DOCTYPE hibernate-mapping PUBLIC "-//Hibernate/Hibernate Mapping DTD 3.0//EN"
"http://hibernate.sourceforge.net/hibernate-mapping-3.0.dtd">
<!-- 
    Mapping file autogenerated by MyEclipse Persistence Tools
-->
<hibernate-mapping>
    <class name="com.yunda.frame.yhgl.entity.OmDuty" table="OM_DUTY">
   		<cache usage="nonstrict-read-write"/>
        <id name="dutyid" type="java.lang.Long">
            <column name="DUTYID"/>
            <generator class="increment" />
        </id>
         <property name="parentduty" type="java.lang.Long">
            <column name="PARENTDUTY" precision="11" scale="0" />
        </property>
        <property name="dutycode" type="java.lang.String">
            <column name="DUTYCODE" length="20" />
        </property>
        <property name="dutyname" type="java.lang.String">
            <column name="DUTYNAME" length="30" />
        </property>
        <property name="dutylevel" type="java.lang.Long">
            <column name="DUTYLEVEL" precision="22" scale="0" />
        </property>
        <property name="dutyseq" type="java.lang.String">
            <column name="DUTYSEQ" length="256" />
        </property>
        <property name="dutytype" type="java.lang.String">
            <column name="DUTYTYPE" />
        </property>
        <property name="isleaf" type="java.lang.String">
            <column name="ISLEAF" length="10" />
        </property>
        <property name="subcount" type="java.lang.Long">
            <column name="SUBCOUNT" precision="10" scale="0" />
        </property>
        <property name="remark" type="java.lang.String">
            <column name="REMARK" length="256" />
        </property>
        <!-- 
        <set name="omPositions" inverse="true">
            <key>
                <column name="DUTYID" precision="10" scale="0" />
            </key>
            <one-to-many class="com.yunda.system.omorganization.entity.OmPosition" />
        </set>
        <set name="omDuties" inverse="true">
            <key>
                <column name="PARENTDUTY" precision="10" scale="0" />
            </key>
            <one-to-many class="com.yunda.system.omduty.entity.OmDuty" />
        </set>
         -->
    </class>
</hibernate-mapping>
